proxy_master/__init__.py
proxy_master/proxy_master.py
proxy_master-2.0.1.dist-info/LICENSE
proxy_master-2.0.1.dist-info/METADATA
proxy_master-2.0.1.dist-info/WHEEL
proxy_master-2.0.1.dist-info/top_level.txt
proxy_master-2.0.1.dist-info/RECORD
