Metadata-Version: 2.1
Name: proxy-master
Version: 2.0.1
Summary: My first package to scrap free proxies from open resources
Author-email: 555Russich <Kutsokondima@yandex.ru>
Project-URL: Homepage, https://github.com/555Russich/proxy_master
Classifier: Programming Language :: Python :: 3
Classifier: License :: OSI Approved :: MIT License
Classifier: Operating System :: OS Independent
Requires-Python: >=3.10
License-File: LICENSE
Requires-Dist: aiohttp
Requires-Dist: bs4
Requires-Dist: lxml
Requires-Dist: pycountry
Requires-Dist: aiohttp-socks
